{
  "schema": 1,
  "packageId": "HydrologicEngineeringCenter.HEC-RAS",
  "resolvedPackageId": null,
  "status": "HasIcon",
  "hasIcon": true,
  "firstSeenUtc": "2026-05-27T17:22:39.3388778Z",
  "lastCheckedUtc": "2026-05-27T17:22:39.3388778Z",
  "lastUpdatedUtc": "2026-05-27T17:22:39.3388778Z",
  "wingetVersion": "v1.29.170-preview",
  "packageVersion": null,
  "manifestSha": null,
  "installerType": null,
  "alreadyInstalled": false,
  "installedByThisRun": true,
  "installSeconds": 50,
  "extractSeconds": 0,
  "uninstallSeconds": 0,
  "durationSeconds": 52,
  "installExitCode": 0,
  "installTimedOut": false,
  "uninstallExitCode": null,
  "uninstallTimedOut": false,
  "failureCategory": null,
  "installAttemptTag": "install-default",
  "extractAttemptCount": 1,
  "extractAttemptScopes": "Both",
  "extractFailureCategory": null,
  "iconCount": 1,
  "iconBytes": 27990.0,
  "appIconFile": "app-icon.ico",
  "canonicalIconSourceName": "HEC-RAS 7.0.{4C3E30D1-8FD1-41FE-B883-221546541205}.ico",
  "canonicalIconBytes": 1,
  "canonicalIconSha256": "9edc341d4d3d3513152b42b2ba59088453a9b37421e19961f3a9dd8e7f210a79",
  "sourceReason": "InstallLocation",
  "extractError": null,
  "installStdErr": null,
  "installAttempts": {
    "tag": "install-default",
    "exitCode": 0,
    "exitHex": "0x00000000",
    "timedOut": false,
    "errorName": null,
    "failureCategory": null
  },
  "icons": {
    "name": "HEC-RAS 7.0.{4C3E30D1-8FD1-41FE-B883-221546541205}.ico",
    "bytes": 27990,
    "sha256": "9edc341d4d3d3513152b42b2ba59088453a9b37421e19961f3a9dd8e7f210a79"
  },
  "run": {
    "startedAtUtc": "2026-05-27T17:22:39.3388778Z",
    "runId": null,
    "runAttempt": null,
    "repository": null
  }
}
