{
  "schema": 1,
  "packageId": "EvanCzaplicki.Elm",
  "resolvedPackageId": null,
  "status": "HasIcon",
  "hasIcon": true,
  "firstSeenUtc": "2026-05-21T19:25:32.8686111Z",
  "lastCheckedUtc": "2026-05-21T19:25:32.8686111Z",
  "lastUpdatedUtc": "2026-05-21T19:25:32.8686111Z",
  "wingetVersion": "v1.29.170-preview",
  "packageVersion": null,
  "manifestSha": null,
  "installerType": null,
  "alreadyInstalled": false,
  "installedByThisRun": true,
  "installSeconds": 8,
  "extractSeconds": 1,
  "uninstallSeconds": 0,
  "durationSeconds": 10,
  "installExitCode": 0,
  "installTimedOut": false,
  "uninstallExitCode": null,
  "uninstallTimedOut": false,
  "failureCategory": null,
  "installAttemptTag": "install-default",
  "extractAttemptCount": 1,
  "extractAttemptScopes": "Both",
  "extractFailureCategory": null,
  "iconCount": 1,
  "iconBytes": 119290.0,
  "appIconFile": "app-icon.ico",
  "canonicalIconSourceName": "Elm 0.19.1.Elm-0.19.1.ico",
  "canonicalIconBytes": 1,
  "canonicalIconSha256": "7f8406a71d8bac20894f979988305ff91cfa2ba76f4f4232b6b3191a8514d091",
  "extractError": null,
  "installStdErr": null,
  "installAttempts": {
    "tag": "install-default",
    "exitCode": 0,
    "exitHex": "0x00000000",
    "timedOut": false,
    "errorName": null,
    "failureCategory": null
  },
  "icons": {
    "name": "Elm 0.19.1.Elm-0.19.1.ico",
    "bytes": 119290,
    "sha256": "7f8406a71d8bac20894f979988305ff91cfa2ba76f4f4232b6b3191a8514d091"
  },
  "run": {
    "startedAtUtc": "2026-05-21T19:25:32.8686111Z",
    "runId": null,
    "runAttempt": null,
    "repository": null
  }
}
