{
  "schema": 1,
  "packageId": "Inkscape.Inkscape",
  "resolvedPackageId": null,
  "status": "HasIcon",
  "hasIcon": true,
  "firstSeenUtc": "2026-05-27T17:59:17.4828790Z",
  "lastCheckedUtc": "2026-05-27T17:59:17.4828790Z",
  "lastUpdatedUtc": "2026-05-27T17:59:17.4828790Z",
  "wingetVersion": "v1.29.170-preview",
  "packageVersion": null,
  "manifestSha": null,
  "installerType": null,
  "alreadyInstalled": false,
  "installedByThisRun": true,
  "installSeconds": 57,
  "extractSeconds": 1,
  "uninstallSeconds": 0,
  "durationSeconds": 59,
  "installExitCode": 0,
  "installTimedOut": false,
  "uninstallExitCode": null,
  "uninstallTimedOut": false,
  "failureCategory": null,
  "installAttemptTag": "install-default",
  "extractAttemptCount": 1,
  "extractAttemptScopes": "Both",
  "extractFailureCategory": null,
  "iconCount": 1,
  "iconBytes": 297358.0,
  "appIconFile": "app-icon.ico",
  "canonicalIconSourceName": "Inkscape.{15D8477C-2591-49DF-B5E9-A69E1CDE95AD}.ico",
  "canonicalIconBytes": 1,
  "canonicalIconSha256": "118cb323cb29c7f73cea4376be503ed7d45103c9bc68ea899ebf82b2a8fdaa5e",
  "sourceReason": "InstallLocation",
  "extractError": null,
  "installStdErr": null,
  "installAttempts": {
    "tag": "install-default",
    "exitCode": 0,
    "exitHex": "0x00000000",
    "timedOut": false,
    "errorName": null,
    "failureCategory": null
  },
  "icons": {
    "name": "Inkscape.{15D8477C-2591-49DF-B5E9-A69E1CDE95AD}.ico",
    "bytes": 297358,
    "sha256": "118cb323cb29c7f73cea4376be503ed7d45103c9bc68ea899ebf82b2a8fdaa5e"
  },
  "run": {
    "startedAtUtc": "2026-05-27T17:59:17.4828790Z",
    "runId": null,
    "runAttempt": null,
    "repository": null
  }
}
